<Properties StartupConfiguration="{2CDCD5DC-5145-4C37-ACEA-CE81D939F89E}|Default">
  <MonoDevelop.Ide.DebuggingService.PinnedWatches />
  <MonoDevelop.Ide.Workspace ActiveConfiguration="Debug" />
  <MonoDevelop.Ide.DebuggingService.Breakpoints>
    <BreakpointStore />
  </MonoDevelop.Ide.DebuggingService.Breakpoints>
  <MonoDevelop.Ide.Workbench ActiveDocument="Food.cs">
    <Files>
      <File FileName="Bullet.cs" Line="73" Column="1" />
      <File FileName="Enemy.cs" Line="64" Column="65" />
      <File FileName="LevelController.cs" Line="37" Column="1" />
      <File FileName="IDamageable.cs" Line="12" Column="6" />
      <File FileName="Food.cs" Line="26" Column="42" />
      <File FileName="Position.cs" Line="1" Column="1" />
      <File FileName="Snake.cs" Line="211" Column="10" />
      <File FileName="GameManager.cs" Line="1" Column="1" />
      <File FileName="Renderer.cs" Line="1" Column="1" />
      <File FileName="IFoodable.cs" Line="11" Column="21" />
      <File FileName="IDeadable.cs" Line="11" Column="22" />
      <File FileName="FoodFactory.cs" Line="28" Column="1" />
    </Files>
    <Pads>
      <Pad Id="ProjectPad">
        <State name="__root__">
          <Node name="MyGame" expanded="True">
            <Node name="MyGame" expanded="True" />
          </Node>
        </State>
      </Pad>
      <Pad Id="MonoDevelop.Debugger.WatchPad">
        <State />
      </Pad>
    </Pads>
  </MonoDevelop.Ide.Workbench>
  <MultiItemStartupConfigurations />
  <MonoDevelop.Ide.ItemProperties.MyGame PreferredExecutionTarget="MonoDevelop.Default" />
</Properties>